components/__init__.py
components/code_executor.py
lessons/__init__.py
lessons/functions.py
lessons/loops.py
lessons/variables.py
tests/__init__.py
tests/test_lessons.py
python_is_easy-1.0.0.dist-info/LICENSE
python_is_easy-1.0.0.dist-info/METADATA
python_is_easy-1.0.0.dist-info/WHEEL
python_is_easy-1.0.0.dist-info/top_level.txt
python_is_easy-1.0.0.dist-info/RECORD
