Metadata-Version: 2.2
Name: python-is-easy
Version: 1.0.0
Summary: An interactive Streamlit app to help people learn Python easily
Home-page: https://github.com/DadaNanjesha/python-is-easy
Author: Dada Nanjesha Gouda Shanbog
Classifier: Programming Language :: Python :: 3
Classifier: Operating System :: OS Independent
License-File: LICENSE
Requires-Dist: streamlit
Dynamic: author
Dynamic: classifier
Dynamic: description
Dynamic: description-content-type
Dynamic: home-page
Dynamic: requires-dist
Dynamic: summary
